pyattck/__init__.py
pyattck/__main__.py
pyattck/attck.py
pyattck/configuration.py
pyattck/datasets.py
pyattck/version.py
pyattck/data/actors/apt10.png
pyattck/data/actors/apt18.png
pyattck/data/actors/apt29.png
pyattck/data/actors/apt32.png
pyattck/data/actors/apt33.png
pyattck/data/actors/apt34.png
pyattck/data/actors/apt37.png
pyattck/data/actors/apt38.png
pyattck/data/actors/apt39.png
pyattck/data/actors/apt40.png
pyattck/data/actors/apt41.png
pyattck/data/actors/apt5.png
pyattck/data/actors/cleaver.png
pyattck/enterprise/__init__.py
pyattck/enterprise/actor.py
pyattck/enterprise/attckobject.py
pyattck/enterprise/control.py
pyattck/enterprise/enterprise.py
pyattck/enterprise/malware.py
pyattck/enterprise/mitigation.py
pyattck/enterprise/tactic.py
pyattck/enterprise/technique.py
pyattck/enterprise/tools.py
pyattck/mobile/__init__.py
pyattck/mobile/actor.py
pyattck/mobile/malware.py
pyattck/mobile/mitigation.py
pyattck/mobile/mobileattck.py
pyattck/mobile/mobileattckobject.py
pyattck/mobile/tactic.py
pyattck/mobile/technique.py
pyattck/mobile/tools.py
pyattck/preattck/__init__.py
pyattck/preattck/actor.py
pyattck/preattck/preattck.py
pyattck/preattck/preattckobject.py
pyattck/preattck/tactic.py
pyattck/preattck/technique.py
pyattck/utils/__init__.py
pyattck/utils/exceptions.py
pyattck/utils/excetions.py
pyattck/utils/logo.py
pyattck/utils/version.py
pyattck_dev-4.0.2.dist-info/LICENSE.md
pyattck_dev-4.0.2.dist-info/METADATA
pyattck_dev-4.0.2.dist-info/WHEEL
pyattck_dev-4.0.2.dist-info/entry_points.txt
pyattck_dev-4.0.2.dist-info/top_level.txt
pyattck_dev-4.0.2.dist-info/RECORD
