Metadata-Version: 2.1
Name: pyattck-dev
Version: 4.0.2
Summary: A Python package to interact with the Mitre ATT&CK Frameworks
Home-page: https://github.com/swimlane/pyattck
Author: Swimlane
Author-email: info@swimlane.com
License: MIT
Keywords: att&ck,mitre,swimlane
Platform: UNKNOWN
Requires-Python: >=3.6, <4
Requires-Dist: requests
Requires-Dist: pendulum (<1.3,>=1.2.3)
Requires-Dist: pyfiglet (==0.8.post1)
Requires-Dist: PyYaml (>=5.4.1)
Requires-Dist: Pillow (==8.2.0)
Requires-Dist: fire (==0.3.1)
